{
    "id": 198,
    "caseId": "20070314000001",
    "count": 3242,
    "shareCount": 3,
    "representImage": 352,
    "representImageInfo": {
        "ext": "JPG",
        "transform": {
            "c": "https://data.boch.gov.tw/old_upload/_upload/Assets_new/building/4826/photo/C055新北市金瓜石太子賓(直轄市定(1)_c.JPG"
        },
        "original": "https://data.boch.gov.tw/old_upload/_upload/Assets_new/building/4826/photo/C055新北市金瓜石太子賓(直轄市定(1).JPG",
        "name": "C055新北市金瓜石太子賓(直轄市定(1)"
    },
    "caseName": "金瓜石太子賓館",
    "classifyCode": "1.1",
    "classifyName": "古蹟",
    "pastHistory": "民國三十四年（1945年）底由國民政府派員接收監理。民國四十四年（1955年）臺灣金銅鑛務局改為臺灣金屬鑛業公司，沿用金瓜石貴賓館，改名為「第一招待所」，或稱「第一賓館」。\n民國七十六年（1987年）臺金公司結束營業，第一賓館乏人照顧，最後撥付台電管理。台灣電力公司接管太子賓館，近20年進行多次維修，太子賓館為台電的北區休閒中心。\n民國九十六年（2007年）黃金博物館館方委託中原大學完成《太子賓館維護調查》，推斷本案之原始形貌，同年由當時的臺北縣政府文化局指定為縣定古蹟（今新北市市定古蹟），古蹟名稱為「金瓜石太子賓館」。",
    "assetsTypeNames": "宅第",
    "otherAssetsType": "",
    "assetsClassifyCode": "1.1.2",
    "assetsClassifyName": "直轄市定古蹟",
    "registerDate": 1173843247000,
    "officialDocNo": "北府文資字第0960001998號函",
    "documents": [
        {
            "fileid": 102126,
            "name": "金瓜石太子賓館、金瓜石神社、水湳洞選煉廠_公告.pdf",
            "thumbnailUrl": "https://data.boch.gov.tw/upload/documents/2021-03-24/23019b11-96a7-4814-9c54-83878a2e2ef7/金瓜石太子賓館、金瓜石神社、水湳洞選煉廠_公告.pdf"
        }
    ],
    "judgeCriteria": [
        "具歷史、文化、藝術價值",
        "重要歷史事件或人物之關係"
    ],
    "registerReason": "一、太子賓館為日治時代為當時皇太子巡視臺灣而建造，型貌依制而建，目前此館大體仍維持原有型貌，空間佈局、材質和結構，具建築之學術價值。\n二、太子賓館其建築物與外部庭園融合成雁行配置方式排列，北側為造景優美的日本庭園，南側有迷你高爾夫球場與射箭場，為臺灣現存保存良好的典型的日式建築。",
    "lawsReference": "<<古蹟指定及廢止審查辦法>>（民國九十五年一月十二日發布）第2條第1項第1、2款",
    "govInstitutionCode": "220",
    "govInstitutionName": "新北市政府",
    "belongCityId": 3,
    "belongCityName": "新北市",
    "belongDistName": "瑞芳區",
    "govInstitution": "新北市政府",
    "govDeptName": "文化局",
    "govDeptPhone": "(02)29603456",
    "govDeptAddress": "新北市板橋區中山路一段161號28樓",
    "cadasters": [
        {
            "fileid": 226759,
            "name": "地籍圖.pdf",
            "thumbnailUrl": "https://data.boch.gov.tw/upload/cadasters/2023-07-06/9bdff116-8421-44a2-bf56-a27cfc718072/地籍圖.pdf"
        }
    ],
    "landUseOtherType": "",
    "nonCityLandUseTypeId": 10,
    "nonCityLandUseTypeName": "特定專用區",
    "nonCityLandUseSubTypeId": 18,
    "nonCityLandUseSubTypeName": "特定目的事業",
    "nonLandUseOtherType": "",
    "locationLandNo": "瑞芳鎮金瓜石段25-1、25-2、25-3、25-4、25-10、25-20地號",
    "buildingFeatures": "從大門（入口）階梯到玄關的的通道範圍，除了入口使用洗石子仿石材地坪幾何式拼組，具有方向性，與建築物的妻切破風、側邊的厚皮香形成入口主景，具有迎賓之意。\n資料來源：市定古蹟金瓜石太子賓館修復及再利用計畫成果報告書",
    "inHouseFeatures": "基本上屬「書院造」樣式，主要由玄關、座敷（床之間、 書院）、襖（不透光拉門）、杉戶、障子及雨戶等元素所組成。另鎔鑄了「數寄屋造」樣式，不使用方柱，而是採用圓柱、保留部分樹皮之木柱或具自然曲線之原木做為室內裝飾。\n太子賓館設有「帳場」（櫃檯）、浴室、 廚房，空間較一般住宅寬敞。內部三組套間由三個（座敷-續間）組成，把隔間拉門打開，便成了舉辦儀式的公共集會場所。\n資料來源：市定古蹟金瓜石太子賓館修復及再利用計畫成果報告書",
    "buildingUsage": "暫停開放參觀。",
    "buildingActualState": "在建築之空間配置、外觀及主要房間等方面，大體上仍保有原有之風貌。\n民國一百一十一年（2022年）修復工程中。",
    "buildingKeyMaintainItem": "修復工程進行中。",
    "bulkTransfer": 0,
    "wenSitename": "新北市立黃金博物館 ",
    "wenSiteaddress": "https://www.gep.ntpc.gov.tw/",
    "belongAddress": "金瓜石金光路6號",
    "isOpenDownload": false,
    "longitude": 121.85835249713047,
    "latitude": 25.107812002776683,
    "representImageSource": "新北市政府文化局 ",
    "landScope": "公告地號：瑞芳區金瓜石段25-1、25-2、25-3、25-4、25-10、25-20地號；重測後地號：瑞芳區黃金段1050、1133、1142、1100、1129、1134地號。(上述公告地號無黃金段，故維持原公告地號)",
    "selfCoverage": "建築物本體、圍牆、圍牆內庭園、圍牆外廣場\n",
    "addresses": [
        {
            "cityName": "新北市",
            "distName": "瑞芳區",
            "id": 130325,
            "caseId": 198,
            "caseStatus": true,
            "cityId": 3,
            "distId": 307,
            "address": "金瓜石金光路6號"
        }
    ],
    "landLots": [
        {
            "cityName": "新北市",
            "distName": "瑞芳區",
            "landNoName": "金瓜石段",
            "noncityLandUseTypeName": "特定專用區",
            "id": 183237,
            "caseId": 198,
            "caseStatus": true,
            "cityId": 3,
            "distId": 307,
            "landNoId": 6209,
            "landSerialNo": "25-1地號",
            "noncityLandUseTypeId": 10,
            "area": "",
            "note": "",
            "cityLandUseId": 2
        },
        {
            "cityName": "新北市",
            "distName": "瑞芳區",
            "landNoName": "金瓜石段",
            "noncityLandUseTypeName": "特定專用區",
            "id": 183238,
            "caseId": 198,
            "caseStatus": true,
            "cityId": 3,
            "distId": 307,
            "landNoId": 6209,
            "landSerialNo": "25-2地號",
            "noncityLandUseTypeId": 10,
            "area": "",
            "note": "",
            "cityLandUseId": 2
        },
        {
            "cityName": "新北市",
            "distName": "瑞芳區",
            "landNoName": "金瓜石段",
            "noncityLandUseTypeName": "特定專用區",
            "id": 183239,
            "caseId": 198,
            "caseStatus": true,
            "cityId": 3,
            "distId": 307,
            "landNoId": 6209,
            "landSerialNo": "25-3地號",
            "noncityLandUseTypeId": 10,
            "area": "",
            "note": "",
            "cityLandUseId": 2
        },
        {
            "cityName": "新北市",
            "distName": "瑞芳區",
            "landNoName": "金瓜石段",
            "noncityLandUseTypeName": "特定專用區",
            "id": 183240,
            "caseId": 198,
            "caseStatus": true,
            "cityId": 3,
            "distId": 307,
            "landNoId": 6209,
            "landSerialNo": "25-4地號",
            "noncityLandUseTypeId": 10,
            "area": "",
            "note": "",
            "cityLandUseId": 2
        },
        {
            "cityName": "新北市",
            "distName": "瑞芳區",
            "landNoName": "金瓜石段",
            "noncityLandUseTypeName": "特定專用區",
            "id": 183241,
            "caseId": 198,
            "caseStatus": true,
            "cityId": 3,
            "distId": 307,
            "landNoId": 6209,
            "landSerialNo": "25-10地號",
            "noncityLandUseTypeId": 10,
            "area": "",
            "note": "",
            "cityLandUseId": 2
        },
        {
            "cityName": "新北市",
            "distName": "瑞芳區",
            "landNoName": "金瓜石段",
            "noncityLandUseTypeName": "特定專用區",
            "id": 183242,
            "caseId": 198,
            "caseStatus": true,
            "cityId": 3,
            "distId": 307,
            "landNoId": 6209,
            "landSerialNo": "25-20地號",
            "noncityLandUseTypeId": 10,
            "area": "",
            "note": "",
            "cityLandUseId": 2
        }
    ],
    "announces": [
        {
            "id": 141922,
            "caseId": 198,
            "caseStatus": true,
            "registerDate": 1173843247000,
            "officialDocNo": "北府文資字第0960001998號",
            "classificationId": 1
        }
    ],
    "geojson": "[{\"type\":\"FeatureCollection\",\"features\":[{\"type\":\"Feature\",\"geometry\":{\"type\":\"MultiPolygon\",\"coordinates\":[]},\"properties\":{\"envelope\":{},\"landLot\":\"新北市瑞芳區金瓜石段25-1地號\"}}],\"notfound\":\"沒有地號資料\"},{\"type\":\"FeatureCollection\",\"features\":[{\"type\":\"Feature\",\"geometry\":{\"type\":\"MultiPolygon\",\"coordinates\":[]},\"properties\":{\"envelope\":{},\"landLot\":\"新北市瑞芳區金瓜石段25-2地號\"}}],\"notfound\":\"沒有地號資料\"},{\"type\":\"FeatureCollection\",\"features\":[{\"type\":\"Feature\",\"geometry\":{\"type\":\"MultiPolygon\",\"coordinates\":[]},\"properties\":{\"envelope\":{},\"landLot\":\"新北市瑞芳區金瓜石段25-3地號\"}}],\"notfound\":\"沒有地號資料\"},{\"type\":\"FeatureCollection\",\"features\":[{\"type\":\"Feature\",\"geometry\":{\"type\":\"MultiPolygon\",\"coordinates\":[]},\"properties\":{\"envelope\":{},\"landLot\":\"新北市瑞芳區金瓜石段25-4地號\"}}],\"notfound\":\"沒有地號資料\"},{\"type\":\"FeatureCollection\",\"features\":[{\"type\":\"Feature\",\"geometry\":{\"type\":\"MultiPolygon\",\"coordinates\":[]},\"properties\":{\"envelope\":{},\"landLot\":\"新北市瑞芳區金瓜石段25-10地號\"}}],\"notfound\":\"沒有地號資料\"},{\"type\":\"FeatureCollection\",\"features\":[{\"type\":\"Feature\",\"geometry\":{\"type\":\"MultiPolygon\",\"coordinates\":[]},\"properties\":{\"envelope\":{},\"landLot\":\"新北市瑞芳區金瓜石段25-20地號\"}}],\"notfound\":\"沒有地號資料\"}]",
    "openVisitType": "不開放參觀",
    "openUpTime": "金瓜石太子賓館因台電公司進行修復工程，目前暫停對外開放。\n",
    "isCharge": false,
    "pastHistorySource": "市定古蹟金瓜石太子賓館修復及再利用計畫成果報告書"
}