{
    "id": 2174,
    "caseId": "20160906000001",
    "count": 3477,
    "shareCount": 2,
    "representImage": 210952,
    "representImageInfo": {
        "ext": "jpg",
        "transform": {
            "c": "https://data.boch.gov.tw/upload/representImageFile/2023-04-11/f69a2b60-2071-473b-b1f6-8ca54422002f/g鳳林-林田神社殘蹟11_c.jpg"
        },
        "original": "https://data.boch.gov.tw/upload/representImageFile/2023-04-11/f69a2b60-2071-473b-b1f6-8ca54422002f/g鳳林-林田神社殘蹟11.jpg",
        "name": "g鳳林-林田神社殘蹟11"
    },
    "caseName": "林田神社殘蹟",
    "classifyCode": "1.2",
    "classifyName": "歷史建築",
    "pastHistory": "　大正2年(1913)，臺灣總督府於今花蓮縣鳳林鎮一帶建立第三座官營移民村─「林田村」。為了提供從日本內地來此的日本移民生活上的需求，陸續規劃小學校、醫療單位等設施。\r\n    宗教部分，大正3年(1914)，當地移民為了宗教上的需求與寄託，林田神社氏子總代表笠井寬二、酒井龜太郎及清平福平等三人，擬於花蓮港廳奉鄉林田村建立神社，於是向臺灣總督佐久間左馬太提出「神社建立申請書」。隔年神社順利動工，並在同年6月6日舉行鎮座儀式。\r\n    當時，林田神社一直是移民村內最重要的信仰中心。到了昭和16年(1941)因日本發太平洋戰爭，臺灣總督府在臺實行「皇民奉公運動時期」，除了要求臺灣人改日本名之外，更要求臺灣人民不得祭拜臺灣原有的民間信仰，必須到神社參拜及神社舉行婚禮，接受神官的祝福等儀式，一直到終戰為止。\r\n   昭和19年(1944)年10月開始，一直到昭和20年(1945)年7月間，花蓮各地遭受到盟軍連番式的空襲，當時的林田神社社務所也遭受到嚴重的波及，毀於戰爭引起的火災。\r\n    戰後，神社一度被改為「鳳林區忠烈祠」，除了沿用日治時期神社設施外，祭神則由當時的日本神祇改為黃花崗七十二烈士。每年三月二九日青年節時，鳳林鎮各級單位及學校都會派員參加紀念大會。根據耆老的回憶，兒時，由老師帶領到忠烈祠來參拜，參拜前得先排隊，然後到手洗舍洗手，洗完手後再到原神社拜殿前的空地排隊，由老師代表向革命先烈致敬。\r\n    民國61年(1972)日本與臺灣斷交之因素，內政部於民國63年(1974)2月25日「臺內民字第573901號函」中，發佈《清除臺灣日據時代表現日本帝國主義優越感之殖民統治紀念遺跡要點》，其中第一項明文規定「1 . 日本神社遺跡應即徹底清除」。當時全臺大部分的神社都在此時期遭到破壞。其中，也包括林田神社在內。\r\n",
    "assetsTypeNames": "其他設施",
    "otherAssetsType": "神社",
    "assetsClassifyCode": "1.2",
    "assetsClassifyName": "歷史建築",
    "registerDate": 1473091200000,
    "officialDocNo": "府文資字第1050167129A號",
    "documents": [
        {
            "fileid": 160603,
            "name": "林田神社殘蹟登錄為歷史建築公告1050906.pdf",
            "thumbnailUrl": "https://data.boch.gov.tw/upload/documents/2022-04-15/2de4467f-7daf-4f39-bc81-4bb15d1230b8/林田神社殘蹟登錄為歷史建築公告1050906.pdf"
        }
    ],
    "judgeCriteria": [
        "具歷史文化價值者",
        "具建築史或技術史之價值者"
    ],
    "registerReason": "（１）為日治時期所建規模較小之神社，雖主體神社業己不存在，但神社台基尚完整，且其圍墻（玉垣）亦為原構，奉獻者氏名多可辨識，具保存價值。 \n\n（２）見證日治時期移民信仰中心之輪廓。",
    "lawsReference": "文化資產保存法第18條、歷史建築登錄廢止審查及輔助辦法第2條第1項第1款、第3款。",
    "govInstitutionCode": "970",
    "govInstitutionName": "花蓮縣政府",
    "belongCityId": 23,
    "belongCityName": "花蓮縣",
    "belongDistName": "鳳林鎮",
    "govInstitution": "花蓮縣文化局",
    "govDeptName": "文化資產科",
    "govDeptPhone": "03-8227121-316",
    "govDeptAddress": "花蓮縣花蓮市文復路6號",
    "cadasters": [
        {
            "fileid": 4425,
            "name": "2016-03-21 20-24-37_00730.jpg",
            "thumbnailUrl": "https://data.boch.gov.tw/old_upload/_upload/Assets_new/building/132806/photo/2016-03-21 20-24-37_00730.jpg"
        }
    ],
    "nonCityLandUseTypeId": 1,
    "nonCityLandUseTypeName": "特定農業區",
    "nonCityLandUseSubTypeId": 13,
    "nonCityLandUseSubTypeName": "遊憩",
    "locationLandNo": "花蓮縣鳳林鎮鳳信段845地號",
    "buildingFeatures": "林田神社目前為花蓮縣境內三大移民村內唯一仍保存「玉垣」、「神社拜殿及本殿基壇」的神社。尤其神社內苑四周由混凝土製成的護欄「玉垣」上頭，每一根大、小玉垣上均寫有奉納者之姓名。此狀況在花蓮縣境內已不見，相當珍貴。\n\n民國103年(2014)，鳳林鎮公所向環保署申請「環保示範區計劃」經費，並參考臺灣總督府公文類纂之大正3年(1914)林田神社長夜燈、鳥居之設計圖進行石燈籠、鳥居的復建，並鋪設參拜道石板等工程。但因昔日第一鳥居位置位於今復興路上，不得不進行改變，於是在今神社入口處重新規劃並興建神明鳥居共兩座，參拜道兩側石燈籠共3對，但因施工人員誤將石燈籠設計圖方型看為圓形，所以造成石燈籠杆部位製成了圓形。另外，為了紀念林田村建村100週年，並在神社路口處旁建立一座「世紀鳳林百年林田紀念碑1914─2014」紀念碑。\n",
    "inHouseFeatures": "無。",
    "buildingUsage": "全天日開放民眾自由參觀。",
    "buildingActualState": "林田神社殘蹟建物本體，僅含神社本殿、拜殿基座及玉垣等，殘蹟現況尚可。",
    "buildingKeyMaintainItem": "殘蹟本體維護及周圍環境整潔。",
    "bulkTransfer": 1,
    "belongAddress": "花蓮縣鳳林鎮鳳信段845地號",
    "isOpenVisit": true,
    "openUpTime": "隨時開放。",
    "isCharge": false,
    "isOpenDownload": true,
    "longitude": 121.465952,
    "latitude": 23.748773,
    "representImageSource": "花蓮縣文化局",
    "landScope": "花蓮縣鳳林鎮鳳信段845地號，面積8,177.68平方公尺。",
    "selfCoverage": "林田神社殘蹟建物本體，僅含神社本殿、拜殿基座及玉垣等。",
    "addresses": [
        {
            "cityName": "花蓮縣",
            "distName": "鳳林鎮",
            "id": 107694,
            "caseId": 2174,
            "caseStatus": true,
            "cityId": 23,
            "distId": 2306,
            "address": "花蓮縣鳳林鎮鳳信段845地號(花蓮縣鳳林鎮大榮里復興路39號旁)"
        }
    ],
    "landLots": [
        {
            "cityName": "花蓮縣",
            "distName": "鳳林鎮",
            "landNoName": "鳳信段",
            "id": 134772,
            "caseId": 2174,
            "caseStatus": true,
            "cityId": 23,
            "distId": 2306,
            "landNoId": 14322,
            "landSerialNo": "845",
            "landownership": 1,
            "area": "8177.68平方公尺",
            "cityLandUseTypeOther": "",
            "noncityLandUseTypeOther": "",
            "note": ""
        }
    ],
    "announces": [
        {
            "id": 115750,
            "caseId": 2174,
            "caseStatus": true,
            "registerDate": 1473091200000,
            "officialDocNo": "府文資字第1050167129A號",
            "classificationId": 1
        }
    ],
    "geojson": "[{\"type\":\"FeatureCollection\",\"features\":[{\"type\":\"Feature\",\"geometry\":{\"type\":\"MultiPolygon\",\"coordinates\":[[[[121.465957030966,23.748600873121454],[121.46570654252015,23.748691536518383],[121.46564030189761,23.748542831420846],[121.46549400518037,23.748593125820687],[121.46543895047913,23.748545909332663],[121.46533059344067,23.748590407851832],[121.46532000448391,23.74838957922403],[121.465226701223,23.74836610393984],[121.46525733451855,23.748298126663204],[121.46516968798564,23.748328348215853],[121.46508360662702,23.74835983819297],[121.46542366179874,23.749293514531466],[121.46649449687834,23.748925757447722],[121.466262492798,23.74837068137054],[121.4659037306123,23.748509419673358],[121.465957030966,23.748600873121454],[121.465957030966,23.748600873121454]]]]},\"properties\":{\"envelope\":{\"left\":\"121.46508360662702\",\"top\":\"23.748298126663204\",\"right\":\"121.46649449687834\",\"bottom\":\"23.749293514531466\"},\"landLot\":\"花蓮縣鳳林鎮鳳信段845\"}}],\"notfound\":[]}]",
    "openVisitType": "完全開放參觀",
    "pastHistorySource": "黃家榮先生提供"
}